tom_superevents/__init__.py
tom_superevents/admin.py
tom_superevents/apps.py
tom_superevents/models.py
tom_superevents/serializers.py
tom_superevents/urls.py
tom_superevents/views.py
tom_superevents/migrations/0001_initial.py
tom_superevents/migrations/0002_superevent.py
tom_superevents/migrations/0003_auto_20210225_0034.py
tom_superevents/migrations/0004_superevent_superevent_type.py
tom_superevents/migrations/0005_auto_20210319_2241.py
tom_superevents/migrations/0006_auto_20210827_2346.py
tom_superevents/migrations/0007_eventcandidate_viable.py
tom_superevents/migrations/0008_eventcandidate_priority.py
tom_superevents/migrations/__init__.py
tom_superevents/static/tom_superevents/css/main.css
tom_superevents/superevent_clients/__init__.py
tom_superevents/superevent_clients/gracedb.py
tom_superevents/superevent_clients/gravitational_wave.py
tom_superevents/templates/tom_superevents/detail.html
tom_superevents/templates/tom_superevents/index.html
tom_superevents/templates/tom_superevents/partials/alert_table.html
tom_superevents/templates/tom_superevents/superevent_detail/gamma_ray_burst.html
tom_superevents/templates/tom_superevents/superevent_detail/gravitational_wave.html
tom_superevents/templates/tom_superevents/superevent_detail/neutrino.html
tom_superevents/templatetags/__init__.py
tom_superevents/templatetags/superevent_extras.py
tom_superevents/tests/__init__.py
tom_superevents/tests/factories.py
tom_superevents/tests/tests.py
tom_superevents_base/__init__.py
tom_superevents_base/asgi.py
tom_superevents_base/settings.py
tom_superevents_base/urls.py
tom_superevents_base/wsgi.py
tom_superevents-0.3.1.dist-info/LICENSE
tom_superevents-0.3.1.dist-info/METADATA
tom_superevents-0.3.1.dist-info/WHEEL
tom_superevents-0.3.1.dist-info/top_level.txt
tom_superevents-0.3.1.dist-info/RECORD
