Metadata-Version: 2.1
Name: tom-superevents
Version: 0.3.1
Summary: Reusable TOMToolkit app to support gravitational wave superevent EM follow-up observations.
Home-page: https://github.com/TOMToolkit/tom_superevents
Author: TOM Toolkit Project
Author-email: dcollom@lco.global, llindstrom@lco.global
License: GPL-3.0 License
Keywords: tomtoolkit,astronomy,astrophysics,cosmology,science
Platform: UNKNOWN
Classifier: Environment :: Web Environment
Classifier: Framework :: Django
Classifier: Framework :: Django :: 3.1
Classifier: Intended Audience :: Developers
Classifier: Intended Audience :: Science/Research
Classifier: License :: OSI Approved :: GNU General Public License v3 or later (GPLv3+)
Classifier: Operating System :: OS Independent
Classifier: Programming Language :: Python
Classifier: Programming Language :: Python :: 3
Classifier: Programming Language :: Python :: 3 :: Only
Classifier: Programming Language :: Python :: 3.6
Classifier: Programming Language :: Python :: 3.7
Classifier: Programming Language :: Python :: 3.8
Classifier: Topic :: Scientific/Engineering :: Astronomy
Classifier: Topic :: Scientific/Engineering :: Physics
License-File: LICENSE
Requires-Dist: gracedb-sdk (~=0.1)
Requires-Dist: python-dateutil (>=2.8)
Requires-Dist: tomtoolkit (>=2.5)
Requires-Dist: voevent-parse (~=1.0)
Provides-Extra: test
Requires-Dist: factory-boy (~=3.1.0) ; extra == 'test'
Requires-Dist: pytest (>=3.0.3) ; extra == 'test'
